{
  "_fv": 57,
  "_type": "block",
  "definition": {
    "texture": "bat",
    "textureTop": "",
    "textureLeft": "",
    "textureFront": "",
    "textureRight": "",
    "textureBack": "",
    "renderType": 2,
    "customModelName": "bat_teddy:default",
    "rotationMode": 1,
    "enablePitch": false,
    "emissiveRendering": false,
    "displayFluidOverlay": false,
    "itemTexture": "",
    "particleTexture": "",
    "tintType": "No tint",
    "isItemTinted": false,
    "hasTransparency": true,
    "connectedSides": false,
    "transparencyType": "CUTOUT_MIPPED",
    "disableOffset": false,
    "boundingBoxes": [
      {
        "mx": 7.1,
        "my": 3.9,
        "mz": 7.1,
        "Mx": 8.9,
        "My": 5.7,
        "Mz": 8.9,
        "subtract": false
      },
      {
        "mx": 6.8,
        "my": 5.4,
        "mz": 7.4,
        "Mx": 7.7,
        "My": 6.6,
        "Mz": 7.7,
        "subtract": false
      },
      {
        "mx": 8.3,
        "my": 5.4,
        "mz": 7.4,
        "Mx": 9.2,
        "My": 6.6,
        "Mz": 7.7,
        "subtract": false
      },
      {
        "mx": 7.1,
        "my": 0.3,
        "mz": 7.1,
        "Mx": 8.9,
        "My": 3.9,
        "Mz": 8.9,
        "subtract": false
      },
      {
        "mx": 6.5,
        "my": 0.0,
        "mz": 3.2,
        "Mx": 9.5,
        "My": 0.3,
        "Mz": 8.0,
        "subtract": false
      },
      {
        "mx": 4.4,
        "my": 0.0,
        "mz": 8.45,
        "Mx": 7.4,
        "My": 4.8,
        "Mz": 8.75,
        "subtract": false
      },
      {
        "mx": 2.0,
        "my": 0.9,
        "mz": 8.45,
        "Mx": 4.4,
        "My": 4.5,
        "Mz": 8.75,
        "subtract": false
      },
      {
        "mx": 8.6,
        "my": 0.0,
        "mz": 8.45,
        "Mx": 11.6,
        "My": 4.8,
        "Mz": 8.75,
        "subtract": false
      },
      {
        "mx": 11.6,
        "my": 0.9,
        "mz": 8.45,
        "Mx": 14.0,
        "My": 4.5,
        "Mz": 8.75,
        "subtract": false
      }
    ],
    "name": "Bat Teddy",
    "specialInformation": {
      "fixedValue": []
    },
    "hardness": 0.8,
    "resistance": 0.8,
    "hasGravity": false,
    "isWaterloggable": false,
    "creativeTab": {
      "value": "CUSTOM:TAB"
    },
    "destroyTool": "hoe",
    "customDrop": {
      "value": ""
    },
    "dropAmount": 1,
    "useLootTableForDrops": false,
    "requiresCorrectTool": false,
    "enchantPowerBonus": 0.0,
    "plantsGrowOn": false,
    "canRedstoneConnect": false,
    "lightOpacity": 0,
    "material": {
      "value": "CLOTH"
    },
    "tickRate": 0,
    "tickRandomly": false,
    "isReplaceable": false,
    "canProvidePower": false,
    "emittedRedstonePower": {
      "fixedValue": 15.0
    },
    "colorOnMap": "DEFAULT",
    "creativePickItem": {
      "value": ""
    },
    "offsetType": "NONE",
    "aiPathNodeType": "DEFAULT",
    "flammability": 0,
    "fireSpreadSpeed": 0,
    "isLadder": false,
    "slipperiness": 0.6,
    "speedFactor": 1.0,
    "jumpFactor": 1.0,
    "reactionToPushing": "NORMAL",
    "isNotColidable": false,
    "isCustomSoundType": false,
    "soundOnStep": {
      "value": "CLOTH"
    },
    "breakSound": {
      "value": ""
    },
    "fallSound": {
      "value": ""
    },
    "hitSound": {
      "value": ""
    },
    "placeSound": {
      "value": ""
    },
    "stepSound": {
      "value": ""
    },
    "luminance": 0,
    "unbreakable": false,
    "breakHarvestLevel": 0,
    "isBonemealable": false,
    "hasInventory": false,
    "guiBoundTo": "<NONE>",
    "openGUIOnRightClick": false,
    "inventorySize": 9,
    "inventoryStackSize": 64,
    "inventoryDropWhenDestroyed": true,
    "inventoryComparatorPower": true,
    "inventoryOutSlotIDs": [],
    "inventoryInSlotIDs": [],
    "hasEnergyStorage": false,
    "energyInitial": 0,
    "energyCapacity": 400000,
    "energyMaxReceive": 200,
    "energyMaxExtract": 200,
    "isFluidTank": false,
    "fluidCapacity": 8000,
    "fluidRestrictions": [],
    "onRightClicked": {
      "name": "BatTeddyOnBlockRightClicked"
    },
    "generateFeature": false,
    "restrictionBiomes": [],
    "blocksToReplace": [
      {
        "value": "Blocks.STONE#0"
      },
      {
        "value": "Blocks.STONE#1"
      },
      {
        "value": "Blocks.STONE#3"
      },
      {
        "value": "Blocks.STONE#5"
      }
    ],
    "generationShape": "UNIFORM",
    "frequencyPerChunks": 10,
    "frequencyOnChunk": 16,
    "minGenerateHeight": 0,
    "maxGenerateHeight": 64
  }
}