{
  "_fv": 57,
  "_type": "tag",
  "definition": {
    "type": "Items",
    "items": [
      {
        "value": "CUSTOM:DarkOakLogBundle"
      },
      {
        "value": "CUSTOM:DarkOakLogReinforced"
      },
      {
        "value": "Blocks.LOG2#1"
      },
      {
        "value": "CUSTOM:DarkOakLogPillar"
      },
      {
        "value": "CUSTOM:DarkOakLogNailed"
      },
      {
        "value": "CUSTOM:ConnectingDarkOakLogPillar"
      }
    ],
    "blocks": [],
    "functions": [],
    "entities": [],
    "biomes": [],
    "damageTypes": [],
    "name": "dark_oak_logs",
    "namespace": "mod"
  }
}